fastapi_crud_router/__init__.py
fastapi_crud_router/src/__init__.py
fastapi_crud_router/src/crud.py
fastapi_crud_router/src/exceptions/__init__.py
fastapi_crud_router/src/exceptions/database.py
fastapi_crud_router/src/exceptions/model.py
fastapi_crud_router/test/__init__.py
fastapi_crud_router/test/test_crud.py
fastapi_router_crud-0.0.27.dist-info/LICENSE
fastapi_router_crud-0.0.27.dist-info/METADATA
fastapi_router_crud-0.0.27.dist-info/WHEEL
fastapi_router_crud-0.0.27.dist-info/top_level.txt
fastapi_router_crud-0.0.27.dist-info/RECORD
